odoo9_addon_project_issue_timesheet_time_control-9.0.1.0.0-py2.7-nspkg.pth
odoo9_addon_project_issue_timesheet_time_control-9.0.1.0.0.dist-info/DESCRIPTION.rst
odoo9_addon_project_issue_timesheet_time_control-9.0.1.0.0.dist-info/METADATA
odoo9_addon_project_issue_timesheet_time_control-9.0.1.0.0.dist-info/RECORD
odoo9_addon_project_issue_timesheet_time_control-9.0.1.0.0.dist-info/WHEEL
odoo9_addon_project_issue_timesheet_time_control-9.0.1.0.0.dist-info/metadata.json
odoo9_addon_project_issue_timesheet_time_control-9.0.1.0.0.dist-info/namespace_packages.txt
odoo9_addon_project_issue_timesheet_time_control-9.0.1.0.0.dist-info/top_level.txt
odoo_addons/project_issue_timesheet_time_control/README.rst
odoo_addons/project_issue_timesheet_time_control/__init__.py
odoo_addons/project_issue_timesheet_time_control/__openerp__.py
odoo_addons/project_issue_timesheet_time_control/i18n/es.po
odoo_addons/project_issue_timesheet_time_control/models/__init__.py
odoo_addons/project_issue_timesheet_time_control/models/account_analytic_line.py
odoo_addons/project_issue_timesheet_time_control/static/description/icon.png
odoo_addons/project_issue_timesheet_time_control/tests/__init__.py
odoo_addons/project_issue_timesheet_time_control/tests/test_project_issue_timesheet_time_control.py
odoo_addons/project_issue_timesheet_time_control/views/account_analytic_line_view.xml
odoo_addons/project_issue_timesheet_time_control/views/project_issue_view.xml
